geometryYLS/__init__.py
geometryYLS/calculation/__init__.py
geometryYLS/calculation/graphic.py
geometryYLS/calculation/rectangle_cal.py
geometryYLS/calculation/round_cal.py
geometryYLS/description/__init__.py
geometryYLS/description/compare.py
geometryYLS/description/shape.py
geometryYLS/description/size.py
geometryYLS-0.2.dist-info/LICENSE.md
geometryYLS-0.2.dist-info/METADATA
geometryYLS-0.2.dist-info/WHEEL
geometryYLS-0.2.dist-info/top_level.txt
geometryYLS-0.2.dist-info/RECORD
