Metadata-Version: 2.1
Name: geometryYLS
Version: 0.2
Summary: A geomety calculation python package
Home-page: https://github.com/Aliceburg/533-lab4-CI
Author: Yilin and Song
Author-email: sngchng@gmail.com
License: MIT
Platform: UNKNOWN
License-File: LICENSE.md
